problema 5/alarma.v
// Ejercico #5, SOP

module alarmagt_SOP(input wire A, B, C, output wire Y);

wire s1,s2, notB;

not U1(notB, B);

and U1(s1, A, notB);
and U2(s2, A, C);

or U3(Y, s1, s2);

endmodule // alarmagt_SOP

// Ejercico #5 POS
module alarmagt_POS (input wire A, B, C, output wire Y);

wire s1, notB;

not U1(notB, B);

or (s1, notB, C);
and(Y, A, s1);


endmodule //alarmagt_POS

problema 5/alarma_tb.v
// tesbench

module tesbench();

reg p1, p2, p3, p4, p5, p6;
wire led1, led2;

alarmagt_SOP G1(p1, p2, p3, led1);
alarmagt_SOP G2(p4, p5, p6, led2);

initial begin
  #10
  $display("    \n     ");
  $display("A  B  C  | Y");
  $display("---------|--");
  $monitor("%b  %b  %b  | %b", p1, p2, p3, led1);

  p1 = 0; p2 = 0; p3 = 0;
  #1 p3 = 1;
  #1 p2 = 1; p3 = 0;
  #1 p2 = 1; p3 = 1;
  #1 p1 = 1; p2 = 0; p3 = 0;
  #1 p1 = 1; p2 = 0; p3 = 1;
  #1 p1 = 1; p2 = 1; p3 = 0;
  #1 p1 = 1; p2 = 1; p3 = 1;
  end

  initial begin

  #20
  $display("    \n     ");
  $display("A  B  C  | Y");
  $display("---------|--");
  $monitor("%b  %b  %b  | %b", p4, p5, p6, led2);

  p4 = 0; p5 = 0; p6 = 0;
  #1 p6 = 1;
  #1 p5 = 1; p6 = 0;
  #1 p5 = 1; p6 = 1;
  #1 p4 = 1; p5 = 0; p6 = 0;
  #1 p4 = 1; p5 = 0; p6 = 1;
  #1 p4 = 1; p5 = 1; p6 = 0;
  #1 p4 = 1; p5 = 1; p6 = 1;
  end

  initial
  #40 $finish;

  initial begin
$dumpfile("alarma_tb.vcd");
$dumpvars(0, tesbench);
end


endmodule

Laboratorio 4/problema 5/alarma_tb.vcd
$date
	Sun Aug 09 17:37:51 2020
$end
$version
	Icarus Verilog
$end
$timescale
	1s
$end
$scope module tesbench $end
$var wire 1 ! led2 $end
$var wire 1 " led1 $end
$var reg 1 # p1 $end
$var reg 1 $ p2 $end
$var reg 1 % p3 $end
$var reg 1 & p4 $end
$var reg 1 ' p5 $end
$var reg 1 ( p6 $end
$scope module G1 $end
$var wire 1 # A $end
$var wire 1 $ B $end
$var wire 1 % C $end
$var wire 1 " Y $end
$var wire 1 ) notB $end
$var wire 1 * s1 $end
$var wire 1 + s2 $end
$upscope $end
$scope module G2 $end
$var wire 1 & A $end
$var wire 1 ' B $end
$var wire 1 ( C $end
$var wire 1 ! Y $end
$var wire 1 , notB $end
$var wire 1 - s1 $end
$var wire 1 . s2 $end
$upscope $end
$upscope $end
$enddefinitions $end
#0
$dumpvars
x.
x-
x,
x+
x*
x)
x(
x'
x&
x%
x$
x#
x"
x!
$end
#10
0"
1)
0*
0+
0%
0$
0#
#11
1%
#12
0)
0%
1$
#13
1%
#14
1"
1*
1)
0%
0$
1#
#15
1+
1%
#16
0"
0*
0+
0)
0%
1$
#17
1"
1+
1%
#20
0!
1,
0-
0.
0(
0'
0&
#21
1(
#22
0,
0(
1'
#23
1(
#24
1!
1-
1,
0(
0'
1&
#25
1.
1(
#26
0!
0-
0.
0,
0(
1'
#27
1!
1.
1(
