Laboratorio #8/Lab #8 ROM/ROM.v
// Laboratorio #8 -- Memoria ROM 4k x8

module ROM4k(  input [11:0] addr, output [7:0] data );


reg [7:0] merom [0:4095];     // Registro de la memoria

assign data = merom [addr];

initial begin         // Se guardan los datos aleatorios

    merom[0] = 8'h88;
    merom[1] = 8'h75;
    merom[2] = 8'h55;
    merom[3] = 8'hCbB;
    merom[4] = 8'hFE;
    merom[5] = 8'hFF;
    merom[6] = 8'hAA;
    merom[7] = 8'h10;
    merom[8] = 8'h7A;
    merom[9] = 8'hC8;
    merom[10] = 8'h77;

 end

endmodule // ROM4k

Laboratorio #8/Lab #8 ROM/ROM_tb.v
// Testbench del la ROM
`define simulation

module testbench();

reg [11:0] addr;    // regisro de la ROM
wire [7:0] data;    // salida de los datos

ROM4k ROM(addr, data);

initial begin     // inicio para mostrar los datos
  addr=0;

  $display("addr\tdata\t");         // se muestan los datos en el diagrama de timing
  $monitor("%d\t%h", addr, data);

  #1 addr=0;
  #1 addr=1;
  #1 addr=2;
  #1 addr=3;
  #1 addr=4;
  #1 addr=5;
  #1 addr=6;
  #1 addr=7;
  #1 addr=8;
  #1 addr=9;
  #1 addr=10;

 end

 initial begin
   // Mostrar los resultdos en los diagramas de timng
   $dumpfile("ROM_tb.vcd");
   $dumpvars(0, testbench);

 end
endmodule

Laboratorio #8/Lab #8 ROM/ROM_tb.vcd
$date
	Sat Oct 24 23:27:27 2020
$end
$version
	Icarus Verilog
$end
$timescale
	1s
$end
$scope module testbench $end
$var wire 8 ! data [7:0] $end
$var reg 12 " addr [11:0] $end
$scope module ROM $end
$var wire 12 # addr [11:0] $end
$var wire 8 $ data [7:0] $end
$upscope $end
$upscope $end
$enddefinitions $end
#0
$dumpvars
b10001000 $
b0 #
b0 "
b10001000 !
$end
#2
b1110101 !
b1110101 $
b1 "
b1 #
#3
b1010101 !
b1010101 $
b10 "
b10 #
#4
b10111011 !
b10111011 $
b11 "
b11 #
#5
b11111110 !
b11111110 $
b100 "
b100 #
#6
b11111111 !
b11111111 $
b101 "
b101 #
#7
b10101010 !
b10101010 $
b110 "
b110 #
#8
b10000 !
b10000 $
b111 "
b111 #
#9
b1111010 !
b1111010 $
b1000 "
b1000 #
#10
b11001000 !
b11001000 $
b1001 "
b1001 #
#11
b1110111 !
b1110111 $
b1010 "
b1010 #
