Laboratorio #9/Ejercicio #5 - ROOM/ROOM.v
// Ejercicio #5  memoria rom con un case

module ROM (address, enable, read, data);

input [3:0] address ;
input read, enable;
output  [7:0] data;

reg [7:0]data ;

always @ ( enable or read or address ) begin

	case (address)
	0 : data = 10;
	 1 : data = 55;
	 2 : data = 244;
	 3 : data = 0;
	 4 : data = 1;
	 5 : data = 8'hff;
	 6 : data = 8'h11;
	 7 : data = 8'h1;
	 8 : data = 8'h10;
	 9 : data = 8'h0;
	 10 : data = 8'h10;
	 11 : data = 8'h15;
	 12 : data = 8'h60;
	 13 : data = 8'h90;
	 14 : data = 8'h70;
	 15 : data = 8'h90;

	endcase
end

endmodule //ROM

Laboratorio #9/Ejercicio #5 - ROOM/ROOM_tb.v
// Testbench
`define simulation

module testbench ();

reg [3:0]address;
reg read,enable;

wire [7:0]data;

ROM U1(address, enable, read, data);

initial begin

$display("Memoria ROM");
	$display("address |  data");         // se muestan los datos en el diagrama de timing
	$monitor("%d\t%d\t",address, data);

	#5 	address=0;
	#5 	address=1;
	#5 	address=2;
	#5 	address=3;
	#5 	address=4;
	#5 	address=5;
	#5 	address=6;
	#5 	address=7;
	#5 	address=8;
	#5 	address=9;
	#5 	address=10;
	#5 	address=11;
	#5 	address=12;
	#5 	address=13;
	#5 	address=14;
	#5 	address=15;

end

initial begin
	$dumpfile("ROOM_tb.vcd");
	$dumpvars(0, testbench);
end

endmodule //Testbench

Laboratorio #9/Ejercicio #5 - ROOM/ROOM_tb.vcd
$date
	Sat Oct 31 04:13:18 2020
$end
$version
	Icarus Verilog
$end
$timescale
	1s
$end
$scope module testbench $end
$var wire 8 ! data [7:0] $end
$var reg 4 " address [3:0] $end
$var reg 1 # enable $end
$var reg 1 $ read $end
$scope module U1 $end
$var wire 4 % address [3:0] $end
$var wire 1 # enable $end
$var wire 1 $ read $end
$var reg 8 & data [7:0] $end
$upscope $end
$upscope $end
$enddefinitions $end
#0
$dumpvars
bx &
bx %
x$
x#
bx "
bx !
$end
#5
b1010 !
b1010 &
b0 "
b0 %
#10
b110111 !
b110111 &
b1 "
b1 %
#15
b11110100 !
b11110100 &
b10 "
b10 %
#20
b0 !
b0 &
b11 "
b11 %
#25
b1 !
b1 &
b100 "
b100 %
#30
b11111111 !
b11111111 &
b101 "
b101 %
#35
b10001 !
b10001 &
b110 "
b110 %
#40
b1 !
b1 &
b111 "
b111 %
#45
b10000 !
b10000 &
b1000 "
b1000 %
#50
b0 !
b0 &
b1001 "
b1001 %
#55
b10000 !
b10000 &
b1010 "
b1010 %
#60
b10101 !
b10101 &
b1011 "
b1011 %
#65
b1100000 !
b1100000 &
b1100 "
b1100 %
#70
b10010000 !
b10010000 &
b1101 "
b1101 %
#75
b1110000 !
b1110000 &
b1110 "
b1110 %
#80
b10010000 !
b10010000 &
b1111 "
b1111 %
