Proyecto Final/FFD_2.v

//--------------------------------------- Acumulador --------------------------------------------

module FF_D (input clk, reset, enabled, input [3:0] D, output reg [3:0] Q);

    always @ (posedge clk, posedge reset)
        if (reset)
            Q <= 4'b0000;
        else if (enabled)
            Q <= D;

endmodule

Proyecto Final/ALU.v

//------------------------------------------------- ALU--------------------------------------------------------

module ALU(input [3:0] A, B, input [2:0] F,  output C, Z, output [3:0] S);

    reg [4:0] regS;

    always @ (A, B, F)
        case (F)
            3'b000: regS = A;
            3'b001: regS = A - B;
            3'b010: regS = B;
            3'b011: regS = A + B;
            3'b100: regS = {1'b0, ~(A & B)};
            default: regS = 5'b10101;
        endcase

    assign S = regS[3:0];
    assign C = regS[4];
    assign Z = ~(regS[3] | regS[2] | regS[1] | regS[0]);

endmodule

Proyecto Final/Buffer.v

//----------------------------------------- Bus_Driver -----------------------------------------------------

module Buffer(input enabled, input [3:0] A, output [3:0] Y);

    assign Y = enabled ? A : 4'bz;

endmodule

Proyecto Final/Fetch.v

//------------------------------------------------- Fetch -----------------------------------------------------

module Fetch (input clk, reset, enabled, input [7:0] En, output reg [7:0] Ou);

    always @ (posedge clk, posedge reset)
        if (reset)
            Ou <= 8'b0000;
        else if (enabled)
            Ou <= En;

endmodule

Proyecto Final/ROM.v

//-----------------------------------------------ROM  64x8 -----------------------------------------------

module ROM (input [11:0] address, output [7:0] data);

    reg [7:0] memory [0:4096];

    initial
        $readmemb("memory.list", memory);

    assign data = memory[address];

endmodule

Proyecto Final/Counter.v
//---------------------------------------- Program Counter  --------------------------------------------

module Counter (input clk, reset, enabled, load, input [11:0] load_Data, output reg [11:0] out_Val);

    always @ (posedge clk, posedge reset) begin
        if (reset)
            out_Val <= 12'b0;
        else if (load)
            out_Val <=  load_Data;
        else if (enabled)
            out_Val <= out_Val + 1;
    end

endmodule

Proyecto Final/PROC.v
//    Universidad del valle de Guatemala
//		Electronica Digital
//		Yefry Elias Sajquiy vargas  - 18748
// 		Proyecto final - Procesador

// Conexion de los modulos

module proyec_F (input clk, reset, enCounter, enFetch, load,// enBuf1, enBuf2, enAccu,
  //  bus dirver, FFD_2, ALu
            //input [2:0]F,
            //input [3:0] busInput,
            //output C,Z,
            //output [3:0] busOutput, accu,

// contador, ROM, Fetch
            input [11:0] counter12bit,
            output [3:0] instr, oprnd,
            output [7:0] program_byte);


    wire [11:0] PC;
    //wire [3:0] data_bus, aluResult;

// LLegan los datos de la RAM
//conexion de  puertos del program counter -> input clk, reset, enabled, load, input [11:0] loadData, output reg [11:0] outValue
    Counter U1(.clk(clk), .reset(reset), .enabled(enCounter), .load(load), .load_Data(counter12bit), .out_Val(PC));

//Los daros llegan del program counter
    // conexxiones puertos de ROM -> input [11:0] address, output [7:0] data
    ROM U2 (PC, program_byte);

//Datos llegan de la ROM
    // puertos de  Fetch -> input clk, reset, enabled, input [7:0] D, output reg [7:0] Q
    Fetch U3 (clk, reset, enFetch, program_byte, {instr, oprnd});

//Datos pasan al Bus Driver  de 4 bits, LLega del Fetch --- BUS DRIVER 1
    Buffer U4(enBuf1, busInput, data_bus);

//Datos pasan al Bus Driver  de 4 bits - Salida de la ALU --- BUS DRIVER  2
    Buffer U5(enBuf2, aluResult, busOutput);

// ALU de 4 Bists de entrada, llegan del BUS DRIBER 1 y pasan ala salida y al al Acumulador
// entrada tambien del acumulado
    ALU U6(.A(accu), .B(data_bus), .F(F), .C(C),.Z(Z), .S(aluResult));

//ACUMULADOR -- flip fliop de 4 bits, datos llegan de la alu y regresan a la misma
    FF_D U7(clk, reset, enAccu, aluResult, accu);


endmodule //proyec_F

Proyecto Final/PROC_tb.v
module testbench();

    reg clk, reset, enCounter, enFetch, load;
    reg [11:0] counter12bit;
    wire [3:0] instr, oprnd;
    wire [7:0] program_byte;

    // Puertos del ej01 input clk, reset, enCounter, enFetch, load, input [11:0] counter12bit, output [3:0] instr, oprnd, output [7:0] program_byte
    proyec_F U1 (clk, reset, enCounter, enFetch, load, counter12bit, instr, oprnd, program_byte);

    always
        #5 clk = ~clk;

    initial
        #100 $finish;

    initial begin
        $display("");
        $monitor("",);
        clk = 0; reset = 0; enCounter = 0; enFetch = 0; load = 0; counter12bit = 12'h000;
        #2 reset = 1;
        #1 reset = 0;

        // Primera prueba será verificar el contador + ROM
        // Esto es sencillamente ver que con cada flanco de reloj se vea un
        // nuevo dato en program_byte. No se agrega un delay de intención.
        // Ya que enFetch = 0 la salida debe ser 4'b0000 todo el tiempo
        enCounter = 1;

        // La siguiente prueba es hacer el 'load' del contador.
        // Saltamos a la localidad 0x123.
        // El enCounter lo dejamos a propósito en 1 para verificar que el load
        // tenga preferencia sobre el conteo. Se espera tener el valor de la
        // localidad de memoria 0x123 en el program_byte
        #20
        counter12bit = 12'h123;
        load = 1;

        // Se deshabilita el load y se permite el conteo de un par de localidades
        // de memoria.
        // NOTA: En este punto me percaté que las únicas señales que deben
        // estar en la lista de sensibilidad del contador son clk y reset.
        // Si se agrega el bit de load o de los 12 bits de entrada produce resultados
        // que podrían causar conflictos con el procesador. En este momento no
        // he hecho pruebas con el procesador, pero es algo importante que tener
        // en cuenta.
        #10
        load = 0;
        counter12bit = 12'h00A;

        // Se deshabilita el conteo y se habilita el Fetch
        // En este momento en instr y oprnd deberían estar los mismos valores
        // que en el program_byte. El program_byte ya no cambia porque el conteo
        // se apagó.
        #10
        enCounter = 0;
        enFetch = 1;

    end

    initial begin
        $dumpfile("PROC_tb.vcd");
        $dumpvars(0, testbench);
    end

endmodule

Proyecto Final/PROC_tb.vcd
$date
	Wed Nov 18 20:36:44 2020
$end
$version
	Icarus Verilog
$end
$timescale
	1s
$end
$scope module testbench $end
$var wire 8 ! program_byte [7:0] $end
$var wire 4 " oprnd [3:0] $end
$var wire 4 # instr [3:0] $end
$var reg 1 $ clk $end
$var reg 12 % counter12bit [11:0] $end
$var reg 1 & enCounter $end
$var reg 1 ' enFetch $end
$var reg 1 ( load $end
$var reg 1 ) reset $end
$scope module U1 $end
$var wire 1 $ clk $end
$var wire 12 * counter12bit [11:0] $end
$var wire 1 + enAccu $end
$var wire 1 , enBuf1 $end
$var wire 1 - enBuf2 $end
$var wire 1 & enCounter $end
$var wire 1 ' enFetch $end
$var wire 1 ( load $end
$var wire 1 ) reset $end
$var wire 8 . program_byte [7:0] $end
$var wire 4 / oprnd [3:0] $end
$var wire 4 0 instr [3:0] $end
$var wire 1 1 data_bus $end
$var wire 1 2 busOutput $end
$var wire 1 3 aluResult $end
$var wire 1 4 accu $end
$var wire 1 5 Z $end
$var wire 12 6 PC [11:0] $end
$var wire 1 7 C $end
$scope module U1 $end
$var wire 1 $ clk $end
$var wire 1 & enabled $end
$var wire 1 ( load $end
$var wire 12 8 load_Data [11:0] $end
$var wire 1 ) reset $end
$var reg 12 9 out_Val [11:0] $end
$upscope $end
$scope module U2 $end
$var wire 12 : address [11:0] $end
$var wire 8 ; data [7:0] $end
$upscope $end
$scope module U3 $end
$var wire 8 < En [7:0] $end
$var wire 1 $ clk $end
$var wire 1 ' enabled $end
$var wire 1 ) reset $end
$var reg 8 = Ou [7:0] $end
$upscope $end
$scope module U4 $end
$var wire 4 > A [3:0] $end
$var wire 1 , enabled $end
$var wire 4 ? Y [3:0] $end
$upscope $end
$scope module U5 $end
$var wire 4 @ A [3:0] $end
$var wire 1 - enabled $end
$var wire 4 A Y [3:0] $end
$upscope $end
$scope module U6 $end
$var wire 4 B A [3:0] $end
$var wire 4 C B [3:0] $end
$var wire 3 D F [2:0] $end
$var wire 1 5 Z $end
$var wire 4 E S [3:0] $end
$var wire 1 7 C $end
$var reg 5 F regS [4:0] $end
$upscope $end
$scope module U7 $end
$var wire 4 G D [3:0] $end
$var wire 1 $ clk $end
$var wire 1 + enabled $end
$var wire 1 ) reset $end
$var reg 4 H Q [3:0] $end
$upscope $end
$upscope $end
$upscope $end
$enddefinitions $end
#0
$dumpvars
bx H
b1 G
b10101 F
b101 E
b0z D
b0z C
b0x B
bx A
b1 @
bxz ?
b0z >
bx =
bx <
bx ;
bx :
bx 9
b0 8
17
bx 6
05
x4
13
x2
z1
bx 0
bx /
bx .
z-
z,
z+
b0 *
0)
0(
0'
0&
b0 %
0$
bx #
bx "
bx !
$end
#2
b0 "
b0 /
b0 #
b0 0
b0 B
04
b11110101 !
b11110101 .
b11110101 ;
b11110101 <
b0 6
b0 9
b0 :
b0 =
b0 H
1)
#3
1&
0)
#5
b1101010 !
b1101010 .
b1101010 ;
b1101010 <
b1 6
b1 9
b1 :
1$
#10
0$
#15
b1111 !
b1111 .
b1111 ;
b1111 <
b10 6
b10 9
b10 :
1$
#20
0$
#23
1(
b100100011 %
b100100011 *
b100100011 8
#25
b10010110 !
b10010110 .
b10010110 ;
b10010110 <
b100100011 6
b100100011 9
b100100011 :
1$
#30
0$
#33
b1010 %
b1010 *
b1010 8
0(
#35
b1101001 !
b1101001 .
b1101001 ;
b1101001 <
b100100100 6
b100100100 9
b100100100 :
1$
#40
0$
#43
1'
0&
#45
b1001 "
b1001 /
b110 #
b110 0
b1101001 =
1$
