Proyecto Final/Buffer.v

//----------------------------------------- Bus_Driver -----------------------------------------------------
// Buffer tri estado se usa para el paso de los bits que los redirecciona

module Buffer_3state (input [3:0] in, input enabled_buf, output [3:0] out_buf);

    assign out_buf = (enabled_buf) ? in : 4'bzzzz;

endmodule

Proyecto Final/FFD_2.v

//------------------------------------------- Acumulador --------------------------------------------------

module Acumulador (input clk, enabled_Acumulador, reset, input [3:0] in_acumulador, output [3:0] out_Acumulador);
reg [3:0] out_Acumulador;

//  Se verifica el cambio del clock , con el enabled_Acumulador es igaul a 1, permite el paso del valor acumulado de la ALU
always @ (posedge clk or posedge reset) begin
  if ( enabled_Acumulador == 1) begin
    out_Acumulador = in_acumulador;
  end
  if (reset == 1) begin
    out_Acumulador = 4'b0000;
  end
end
endmodule

Proyecto Final/ALU.v

//------------------------------------------------- ALU--------------------------------------------------------

module ALU (input [3:0] A, B, input [2:0] S, output [3:0] Y, output Z_alu, C_alu);

// P es la variable de 4 bits que resivisa  el valor de las operaciones y  pasa a la salida
  reg [4:0] P;

  assign Y = P[3:0];
  assign C_alu = (S[0]) ? P[4]:0;
  assign Z_alu = (P[3:0] == 0);

  always @ ( A, B, S ) begin

//S guarda la dirección de las operaciones los cuales leera la ALU y procedera a realizar el calculo
    case (S)
      3'b000: P = A;
      3'b001: P = A-B;
      3'b010: P = B;
      3'b011: P = A+B;
      3'b100: P = ~(A&B);

     default:
            P = 0;
    endcase
  end
endmodule

Proyecto Final/RAM.v

//---------------------------- Memoria RAM -------------------------------------------------------------

module RAM (input csRAM, weRAM, input [11:0] address_RAM, inout [3:0] data_RAM);
    reg [3:0] out_data;
    reg [3:0] memory [0:4095];

//  Comiezo del proceso de la RAM
    assign data_RAM = (csRAM & ~weRAM) ? out_data : 4'bzzzz;

    always @ ( address_RAM, csRAM, weRAM ) begin
      if ( csRAM & ~weRAM ) begin
        out_data = memory[address_RAM];
        end
    end

    always @ (csRAM, weRAM, data_RAM, address_RAM) begin

        if ( csRAM & weRAM  ) begin
          memory[address_RAM] = data_RAM;
        end
    end

endmodule

Proyecto Final/Decode.v
module Decode ( input [3:0] instr, input C, Ze, phase, output incPC, loadPC, loadA, loadFlags, csRAM, weRAM, oeALU, oeIN, oeOprnd, loadOut,
  output [2:0] S,output [11:0] out);

  reg incPC, loadPC, loadA, loadFlags, csRAM, weRAM, oeALU, oeIN, oeOprnd, loadOut;
  reg [2:0] S;
  reg [6:0] Din;

  always @ (instr or phase) begin

    Din = {instr, C, Ze, phase};

    casez (Din)

      7'b??????0:
      begin
        incPC = 1;
        loadPC = 0;
        loadA = 0;
        loadFlags = 0;
        csRAM = 0;
        weRAM = 0;
        oeALU = 1;
        oeIN = 0;
        oeOprnd = 0;
        loadOut = 0;
        S = 3'b000;
      end

      //JC
      7'b00001?1:
      begin
        incPC = 0;
        loadPC = 1;
        loadA = 0;
        loadFlags = 0;
        csRAM = 0;
        weRAM = 0;
        oeALU = 1;
        oeIN = 0;
        oeOprnd = 0;
        loadOut = 0;
        S = 3'b000;
      end

      //JC2
      7'b00000?1:
      begin
        incPC = 1;
        loadPC = 0;
        loadA = 0;
        loadFlags = 0;
        csRAM = 0;
        weRAM = 0;
        oeALU = 1;
        oeIN = 0;
        oeOprnd = 0;
        loadOut = 0;
        S = 3'b000;
      end

      //JNC
      7'b00011?1:
      begin
        incPC = 1;
        loadPC = 0;
        loadA = 0;
        loadFlags = 0;
        csRAM = 0;
        weRAM = 0;
        oeALU = 1;
        oeIN = 0;
        oeOprnd = 0;
        loadOut = 0;
        S = 3'b000;
      end

      //JNC2
      7'b00010?1:
      begin
        incPC = 0;
        loadPC = 1;
        loadA = 0;
        loadFlags = 0;
        csRAM = 0;
        weRAM = 0;
        oeALU = 1;
        oeIN = 0;
        oeOprnd = 0;
        loadOut = 0;
        S = 3'b000;
      end

      //CMPI
      7'b0010??1:
      begin
        incPC = 0;
        loadPC = 0;
        loadA = 0;
        loadFlags = 1;
        csRAM = 0;
        weRAM = 0;
        oeALU = 0;
        oeIN = 0;
        oeOprnd = 1;
        loadOut = 0;
        S = 3'b001;
      end

      //CMPM
      7'b0011??1:
      begin
        incPC = 1;
        loadPC = 0;
        loadA = 0;
        loadFlags = 1;
        csRAM = 1;
        weRAM = 0;
        oeALU = 0;
        oeIN = 0;
        oeOprnd = 0;
        loadOut = 0;
        S = 3'b001;
      end

      //LIT
      7'b0100??1:
      begin
        incPC = 0;
        loadPC = 0;
        loadA = 1;
        loadFlags = 1;
        csRAM = 0;
        weRAM = 0;
        oeALU = 0;
        oeIN = 0;
        oeOprnd = 1;
        loadOut = 0;
        S = 3'b010;
      end

      //IN
      7'b0101??1:
      begin
        incPC = 0;
        loadPC = 0;
        loadA = 1;
        loadFlags = 1;
        csRAM = 0;
        weRAM = 0;
        oeALU = 0;
        oeIN = 1;
        oeOprnd = 0;
        loadOut = 0;
        S = 3'b010;
      end

      //LD
      7'b0110??1:
      begin
        incPC = 1;
        loadPC = 0;
        loadA = 1;
        loadFlags = 1;
        csRAM = 1;
        weRAM = 0;
        oeALU = 0;
        oeIN = 0;
        oeOprnd = 0;
        loadOut = 0;
        S = 3'b010;
      end

      //ST
      7'b0111??1:
      begin
        incPC = 1;
        loadPC = 0;
        loadA = 0;
        loadFlags = 0;
        csRAM = 1;
        weRAM = 1;
        oeALU = 1;
        oeIN = 0;
        oeOprnd = 0;
        loadOut = 0;
        S = 3'b000;
      end

      //JZ
      7'b1000?11:
      begin
        incPC = 0;
        loadPC = 1;
        loadA = 0;
        loadFlags = 0;
        csRAM = 0;
        weRAM = 0;
        oeALU = 1;
        oeIN = 0;
        oeOprnd = 0;
        loadOut = 0;
        S = 3'b000;
      end

      //JZ2
      7'b1000?01:
      begin
        incPC = 1;
        loadPC = 0;
        loadA = 0;
        loadFlags = 0;
        csRAM = 0;
        weRAM = 0;
        oeALU = 1;
        oeIN = 0;
        oeOprnd = 0;
        loadOut = 0;
        S = 3'b000;
      end

      //JNZ
      7'b1001?11:
      begin
        incPC = 1;
        loadPC = 0;
        loadA = 0;
        loadFlags = 0;
        csRAM = 0;
        weRAM = 0;
        oeALU = 1;
        oeIN = 0;
        oeOprnd = 0;
        loadOut = 0;
        S = 3'b000;
      end

      //JNZ2
      7'b1001?01:
      begin
        incPC = 0;
        loadPC = 1;
        loadA = 0;
        loadFlags = 0;
        csRAM = 0;
        weRAM = 0;
        oeALU = 1;
        oeIN = 0;
        oeOprnd = 0;
        loadOut = 0;
        S = 3'b000;
      end

      //ADDI
      7'b1010??1:
      begin
        incPC = 0;
        loadPC = 0;
        loadA = 1;
        loadFlags = 1;
        csRAM = 0;
        weRAM = 0;
        oeALU = 0;
        oeIN = 0;
        oeOprnd = 1;
        loadOut = 0;
        S = 3'b011;
      end

      //ADDM
      7'b1011??1:
      begin
        incPC = 1;
        loadPC = 0;
        loadA = 1;
        loadFlags = 1;
        csRAM = 1;
        weRAM = 0;
        oeALU = 0;
        oeIN = 0;
        oeOprnd = 0;
        loadOut = 0;
        S = 3'b011;
      end

      //JMP
      7'b1100??1:
      begin
        incPC = 0;
        loadPC = 1;
        loadA = 0;
        loadFlags = 0;
        csRAM = 0;
        weRAM = 0;
        oeALU = 1;
        oeIN = 0;
        oeOprnd = 0;
        loadOut = 0;
        S = 3'b000;
      end

      //out
      7'b1101??1:
      begin
        incPC = 0;
        loadPC = 0;
        loadA = 0;
        loadFlags = 0;
        csRAM = 0;
        weRAM = 0;
        oeALU = 1;
        oeIN = 0;
        oeOprnd = 0;
        loadOut = 1;
        S = 3'b000;
      end

      // NANDI
      7'b1110??1:
      begin
        incPC = 0;
        loadPC = 0;
        loadA = 1;
        loadFlags = 1;
        csRAM = 0;
        weRAM = 0;
        oeALU = 0;
        oeIN = 0;
        oeOprnd = 1;
        loadOut = 0;
        S = 3'b100;
      end

      // NANDM
      7'b1111??1:
      begin
        incPC = 1;
        loadPC = 0;
        loadA = 1;
        loadFlags = 1;
        csRAM = 1;
        weRAM = 0;
        oeALU = 0;
        oeIN = 0;
        oeOprnd = 0;
        loadOut = 0;
        S = 3'b100;
      end
      default: ;
    endcase
  end

  assign out = {incPC, loadPC, loadA, loadFlags, S[2:0], csRAM, weRAM, oeALU, oeIN, oeOprnd, loadOut};

endmodule

Proyecto Final/Phase.v

// --------------------------------------- PHASE -----------------------------------------------------------

module Phase (input clk, reset, output out_ph);
  reg out_ph;

  // El phase permite el control del fetch, con un 1. Tambien permite a otros modulos poder pasar a otro estado en cualquier
  // flanco de reloj

  always @ ( posedge clk or posedge reset) begin

    if (reset) begin
      out_ph = 0;
    end else begin
      out_ph = ~out_ph;
      
      end
  end
endmodule

Proyecto Final/Flags.v

//------------------------------------------ FLAGS -----------------------------------------------------------

module Flags (input clk, enabled_flags, reset, C, Ze, output C_1, Z_1);
  reg C_1, Z_1;

  //C y Z son parte de la combinación de bits necesarios en el decoder para asignarle valores a las señales de control
  
  always @ (posedge clk or posedge reset) begin
    if (reset == 0 & enabled_flags == 1) begin
      C_1 = C;
      Z_1 = Ze;
    end

    if (reset == 1) begin
      C_1 = 0;
      Z_1 = 0;
    end
  end
endmodule

Proyecto Final/Fetch.v

//------------------------------------------------- Fetch -----------------------------------------------------

module Fetch (input clk, enabled_fetch, reset, input [7:0] in_fetch, output [7:0] out_fetch);
  reg [7:0] out_fetch;

    // Se revisa cada cambió de clk y reset, cuando enable es 1 deja pasar el valor
  always @ ( posedge clk or posedge reset ) begin
      if (enabled_fetch == 1 ) begin
        out_fetch = in_fetch;
      end

      if (reset) begin
        out_fetch=0;
      end
  end
endmodule

Proyecto Final/ROM.v

//-----------------------------------------------ROM  64x8 -----------------------------------------------

module ROM (input [11:0] address_ROM, output [7:0] data_ROM);

// salida de 7 bits,direccionamiento a 4096
  reg [7:0] memory [0:4095];


  assign data_ROM = memory [address_ROM];

// Se llama al archivo donde estan las intrucciones del Procesador
  initial begin
      $readmemb("memory.list", memory);
  end
endmodule

Proyecto Final/Counter.v

//---------------------------------------- Program Counter  --------------------------------------------

module Counter (input clk, enabled_counter, reset, load_counter, input [11:0] load_Val, output [11:0] out_Val);

  reg [11:0] count;
  assign out_Val = count;

//Su señal de control es incPC hace que se pueda seguir sel conteo, cuand load_Val es 1 ,se salta instrucciones y ejecuta lo que se solicita

//Se comienza con las condiciones
  always @ (posedge clk or posedge reset) begin
    if (enabled_counter == 1 ) begin
      count = count + 1;
    end

    if (enabled_counter == 0) begin
      count = count;
    end

    if (load_counter == 1) begin
      count = load_Val;
    end

    if (reset == 1) begin
      count=0;
    end
  end
endmodule

Proyecto Final/UP.v
//    Universidad del valle de Guatemala
//		Electronica Digital
//		Yefry Elias Sajquiy Vargas  - 18748
// 		Proyecto final - Procesador UP

// Conexion de los modulos

/*`include "ALU.v"
`include "Buffer.v"
`include "Counter.v"
`include "Decode.v"
`include "Fetch.v"
`include "FFD_2.v"
`include "Flags.v"
`include "Phase.v"
`include "RAM.v"
`include "ROM.v"
*/

// Modulo principal para las conexiones del los otros modulos
module UP (input clk, reset, input [3:0] pushbuttons, output phase, c_flag, z_flag, output [3:0] instr, operand, data_bus, FF_out, accu,
                      output [7:0] program_byte, output [11:0] pc, address_ram);

  wire [2:0] S;
  wire [11:0] pc;
  wire incPC, loadPC, phase, loadFlags, c_flag_in, z_flag_in, loadA, csRAM, weRAM, oeALU, oeIN, oeOprnd, loadOut;
  wire [3:0] alu_out;
  wire ph;

  assign address_ram = {operand, program_byte};
  assign phase = ph;


// Se comienza por el modulo del program counter
    Counter     U1(.clk(clk), .enabled_counter(incPC), .reset(reset), .load_counter(loadPC), .load_Val({operand, program_byte}), .out_Val(pc));

// los datos del counter pasan a la memoria ROM
    ROM          U2(.address_ROM(pc), .data_ROM(program_byte));

//Los datos de la ROM pasan al fetch para direccionarlos al decodificador y al bus driver 1
    Fetch          U3(.clk(clk), .enabled_fetch(ph), .reset(reset), .in_fetch(program_byte), .out_fetch({instr, operand}));

//Los flags, son las banderas que pasan al decodificador
    Flags          U4(.clk(clk), .enabled_flags(loadFlags), .reset(reset), .Ze(z_flag_in), .C(c_flag_in), .Z_1(z_flag), .C_1(c_flag));

// El phase permite que haya lectruas en cualquier parte de los tiempos
    Phase          U5(.clk(clk), .reset(reset), .out_ph(ph));

// decodificador oara las instrucciones
    Decode       U6(.instr(instr), .C(c_flag), .Ze(z_flag), .phase(ph), .incPC(incPC), .loadPC(loadPC), .loadA(loadA),
                       .loadFlags(loadFlags), .csRAM(csRAM), .weRAM(weRAM), .oeALU(oeALU), .oeIN(oeIN), .oeOprnd(oeOprnd),
                       .loadOut(loadOut), .S(S));

//Los daros son fuardados en la RAM que Pasan al program counter  y qu ellegan del fetch y de la ROM
    RAM            U7(.csRAM(csRAM), .weRAM(weRAM), .address_RAM({operand, program_byte}), .data_RAM(data_bus));

// Deja pasar los datos del getch para la alu
    Buffer_3state    U8(.in(operand), .enabled_buf(oeOprnd), .out_buf(data_bus));

// Se hacen las operaciones que pasan al Acumulador y al segundo bus driver
   ALU             U9(.A(accu), .B(data_bus), .S(S), .Y(alu_out), .Z_alu(z_flag_in), .C_alu(c_flag_in));

// le ellegan los datos de la Alu
    Acumulador   U10(.clk(clk), .enabled_Acumulador(loadA), .reset(reset), .in_acumulador(alu_out), .out_Acumulador(accu));

   Buffer_3state  U11(.in(alu_out), .enabled_buf(oeALU), .out_buf(data_bus));

   Acumulador    U12(.clk(clk), .enabled_Acumulador(loadOut), .reset(reset), .in_acumulador(data_bus), .out_Acumulador(FF_out));

   Buffer_3state  U13(.in(pushbuttons), .enabled_buf(oeIN), .out_buf(data_bus));

endmodule

Proyecto Final/UP_tb.v
//`include "UP.v"

module testbench();

// Declaracion de variables
 wire Z_ALU;
 real points = 0;
  reg clk = 1, reset;
  reg [3:0] PUSH_BUTTONS;
  wire PHASE, C_FLAG, Z_FLAG;
  wire [3:0] INSTR, OPERAND, DATA_BUS, FFD_OUT, ACCU;
  wire [7:0] PROGRAM_BYTE;
  wire [11:0] PC, ADDRESS_RAM;
  wire [12:0] DECODE;
  wire [3:0] ALU;

// Coneccion del modulo principal ¨UP¨ con  el testbench
  UP uPmodule(.clk(clk),
        .reset(reset),
        .pushbuttons(PUSH_BUTTONS),
        .phase(PHASE),
        .c_flag(C_FLAG),
        .z_flag(Z_FLAG),
        .instr(INSTR),
        .operand(OPERAND),
        .data_bus(DATA_BUS),
        .FF_out(FFD_OUT),
        .accu(ACCU),
        .program_byte(PROGRAM_BYTE),
        .pc(PC),
        .address_ram(ADDRESS_RAM)
        );

// Cambio en el clock cada 5 segundos
  always
  #5 clk = ~clk;


  initial begin
    reset = 0;
    #1 reset = 1;
    #1 reset = 0;
    PUSH_BUTTONS = 4'b0110;
    #1998 $finish;
  end

// comienzo de la lectrua del procesador
  always @ (PHASE) begin

    case ($time)

// -------------------------------------------------------------------------------------------------------------
// Verificacion de las instrucciones del procesador base
// En esta sección se prueban  las instrucciones LIT, IN, OUT, ADDI, NANDI y CMPI
// Se verifica si funciona bien, o funciona mal. Se asignaran los puntos en cada verificacion correcta
// -------------------------------------------------------------------------------------------------------------

      20: begin
        if (ACCU === 4'b1001) begin
          points = points + 70;
         $display("LIT funciona bien. Nota: %f", points); end
        else
          $display("LIT NO funciona bien. Nota: %f", points);
      end

      40: begin
        if (ACCU === PUSH_BUTTONS) begin
          points = points + 33;
           $display(" IN funciona bien. Nota: %f", points); end
        else
          $display(" IN NO funciona bien. Nota: %f", points);
      end

      60: begin
        if (FFD_OUT === ACCU) begin
          points = points + 33;
          $display("OUT funciona bien. Nota: %f", points); end
        else begin
          $display("OUT NO funciona bien. Nota: %f", points); end
      end

      80: begin
        if (ACCU === 4'b1111) begin
          points = points + 33;
           $display("ADDI funciona bien. (sin overflow). Nota: %f", points); end
        else begin
          $display("ADDI NO funciona bien. (sin overflow). Nota: %f", points); end
      end

      100: begin
        if (C_FLAG === 1'b1) begin
          points = points + 66; $display("ADDI funciona bien. (con overflow) Nota: %f", points); end
        else
          $display("ADDI NO funciona bien. (con overflow). Nota: %f", points);
      end

      140: begin
        if (ACCU === (~(4'b1010 & 4'b0101))) begin
          points = points + 33;
          $display("NANDI funciona bien. (sin banderas). Nota: %f", points); end
        else
          $display("NANDI NO funciona bien. (sin banderas) Nota: %f", points);
      end

      160: begin
        if (Z_FLAG) begin
          points = points + 33;
          $display("NANDI funciona bien. (con bandera Z). Nota: %f", points); end
        else
          $display("NANDI NO funciona bien. (con bandera Z) Nota: %f", points);
      end

      200: begin
        if (Z_FLAG & ~C_FLAG) begin
          points = points + 33;
          $display("CMPI funciona bien. (A-B=0 -> Z=1, C=0). Nota: %f", points); end
        else
          $display("CMPI NO funciona bien. (A-B=0 -> Z=1, C=0) Nota: %f", points);
      end

      220: begin
        if (~Z_FLAG & ~C_FLAG) begin
          points = points + 33;
          $display("CMPI funciona bien. (A-B=1 -> Z=0, C=0). Nota: %f", points); end
        else
          $display("CMPI NO funciona bien. (A-B=1 -> Z=0, C=0) Nota: %f", points);
      end

      240: begin
        if (~Z_FLAG & C_FLAG) begin
          points = points + 33;
          $display("CMPI funciona bien. (A-B=-1 -> Z=0, C=1). Nota: %f", points); end
        else
          $display("CMPI NO funciona bien. (A-B=-1 -> Z=0, C=1) Nota: %f", points);
      end

// -------------------------------------------------------------------------------------------------------------
// Verificacion de las instrucciones de la RAM
// En esta sección se prueban  las instrucciones LD, ST, ADDM, NANDM y CMPM
// -------------------------------------------------------------------------------------------------------------

      380: begin
        if (ACCU === 4'hE) begin
          points = points + 80;
          $display("LD y ST funcionan bien. Nota: %f", points); end
        else
          $display("LD y ST NO funcionan bien. Nota: %f", points);
      end

      420: begin
        if (ACCU === 4'hF & ~C_FLAG) begin
          points = points + 20;
          $display("ADDM funciona bien (C=0). Nota: %f", points); end
        else
          $display("ADDM NO funciona bien (C=0). Nota: %f", points);
      end

      440: begin
        if (ACCU === 4'h0 & C_FLAG & Z_FLAG) begin
          points = points + 20;
          $display("ADDM funciona bien (C=1, Z=1). Nota: %f", points); end
        else
          $display("ADDM NO funciona bien (C=1, Z=1). Nota: %f", points);
      end

      480: begin
        if (ACCU === 4'h1 & ~C_FLAG & ~Z_FLAG) begin
          points = points + 20;
          $display("NANDM funciona bien (C=0, Z=0). Nota: %f", points); end
        else
          $display("NANDM NO funciona bien (C=0, Z=0). Nota: %f", points);
      end

      540: begin
        if (ACCU === 4'h0 & ~C_FLAG & Z_FLAG) begin
          points = points + 20;
          $display("NANDM funciona bien (C=0, Z=1). Nota: %f", points); end
        else
          $display("NANDM NO funciona bien (C=0, Z=1). Nota: %f", points);
      end

      600: begin
        if (ACCU === 4'h2 & ~C_FLAG & Z_FLAG) begin
          points = points + 20;
           $display("CMPM funciona bien (A-B=0, Z=1, C=0). Nota: %f", points); end
        else
          $display("CMPM NO funciona bien (A-B=0, Z=1, C=0). Nota: %f", points);
      end

      680: begin
        if (ACCU === 4'h1 & C_FLAG & ~Z_FLAG) begin
          points = points + 20;
           $display("CMPM funciona bien (A-B=-1, Z=0, C=1). Nota: %f", points); end
        else
          $display("CMPM NO funciona bien (A-B=-1, Z=0, C=1). Nota: %f", points);
      end

// -------------------------------------------------------------------------------------------------------------
// Verificacion de las instrucciones de los saltos
// En esta sección se prueban  las instrucciones JMP, JC, JNC, JZ y JNZ
// Para cada comparación se verifican las banderas
// -------------------------------------------------------------------------------------------------------------

      700: begin
        if (PC === 12'h034) begin
          points = points + 60;
          $display("JMP funciona bien. Nota: %f", points); end
        else
          $display("JMP NO funciona bien. Nota: %f", points);
      end

      740: begin
        if (PC === 12'h037) begin
          points = points + 30;
          $display("JC funciona bien con C=0. Nota: %f", points); end
        else
          $display("JC NO funciona bien con C=0. Nota: %f", points);
      end

      760: begin
        if (PC === 12'h039) begin
          points = points + 30;
          $display("JZ funciona bien con Z=0. Nota: %f", points); end
        else
          $display("JZ NO funciona bien con Z=0. Nota: %f", points);
      end

      820: begin
        if (PC === 12'h03F) begin
          points = points + 30;
           $display("JZ funciona bien con Z=1. Nota: %f", points); end
        else
          $display("JZ NO funciona bien con Z=1. Nota: %f", points);
      end

      880: begin
        if (PC === 12'h045) begin
          points = points + 30;
           $display("JC funciona bien con C=1. Nota: %f", points); end
        else

          $display("JC NO funciona bien con C=1. Nota: %f", points);
      end

      940: begin
        if (PC === 12'h049) begin
          points = points + 30;
          $display("JNC funciona bien con C=1. Nota: %f", points); end
        else
          $display("JNC NO funciona bien con C=1. Nota: %f", points);
      end

      960: begin
        if (PC === 12'h04B) begin
          points = points + 30;
          $display("JNZ funciona bien con Z=1. Nota: %f", points); end
        else
          $display("JNZ NO funciona bien con Z=1. Nota: %f", points);
      end

      1000: begin
        if (PC === 12'h050) begin
          points = points +30 ;
           $display("JNC funciona bien con C=0. Nota: %f", points); end
        else
          $display("JNC NO funciona bien con C=0. Nota: %f", points);
      end

      1040: begin
        if (PC === 12'h030) begin
          points = points + 30;
           $display("JNZ funciona bien con Z=1. Nota: %f", points); end
        else
          $display("JNZ NO funciona bien con Z=1. Nota: %f", points);
      end
  endcase
  //fin de las verificaciones

  end

// Se abre GTKwave para los diagramas de timing
  initial begin
    $dumpfile("UP_tb.vcd");
    $dumpvars(0, testbench);
  end

endmodule

Proyecto Final/UP_tb.vcd
$date
	Sun Nov 22 19:35:35 2020
$end
$version
	Icarus Verilog
$end
$timescale
	1s
$end
$scope module testbench $end
$var wire 4 ! DATA_BUS [3:0] $end
$var wire 1 " Z_FLAG $end
$var wire 8 # PROGRAM_BYTE [7:0] $end
$var wire 1 $ PHASE $end
$var wire 12 % PC [11:0] $end
$var wire 4 & OPERAND [3:0] $end
$var wire 4 ' INSTR [3:0] $end
$var wire 4 ( FFD_OUT [3:0] $end
$var wire 1 ) C_FLAG $end
$var wire 12 * ADDRESS_RAM [11:0] $end
$var wire 4 + ACCU [3:0] $end
$var reg 4 , PUSH_BUTTONS [3:0] $end
$var reg 1 - clk $end
$var reg 1 . reset $end
$var real 1 / points $end
$scope module uPmodule $end
$var wire 1 - clk $end
$var wire 4 0 data_bus [3:0] $end
$var wire 1 $ phase $end
$var wire 4 1 pushbuttons [3:0] $end
$var wire 1 . reset $end
$var wire 1 2 z_flag_in $end
$var wire 1 " z_flag $end
$var wire 1 3 weRAM $end
$var wire 8 4 program_byte [7:0] $end
$var wire 1 5 ph $end
$var wire 12 6 pc [11:0] $end
$var wire 4 7 operand [3:0] $end
$var wire 1 8 oeOprnd $end
$var wire 1 9 oeIN $end
$var wire 1 : oeALU $end
$var wire 1 ; loadPC $end
$var wire 1 < loadOut $end
$var wire 1 = loadFlags $end
$var wire 1 > loadA $end
$var wire 4 ? instr [3:0] $end
$var wire 1 @ incPC $end
$var wire 1 A csRAM $end
$var wire 1 B c_flag_in $end
$var wire 1 ) c_flag $end
$var wire 4 C alu_out [3:0] $end
$var wire 12 D address_ram [11:0] $end
$var wire 4 E accu [3:0] $end
$var wire 3 F S [2:0] $end
$var wire 4 G FF_out [3:0] $end
$scope module U1 $end
$var wire 1 - clk $end
$var wire 12 H load_Val [11:0] $end
$var wire 12 I out_Val [11:0] $end
$var wire 1 . reset $end
$var wire 1 ; load_counter $end
$var wire 1 @ enabled_counter $end
$var reg 12 J count [11:0] $end
$upscope $end
$scope module U10 $end
$var wire 1 - clk $end
$var wire 1 . reset $end
$var wire 4 K in_acumulador [3:0] $end
$var wire 1 > enabled_Acumulador $end
$var reg 4 L out_Acumulador [3:0] $end
$upscope $end
$scope module U11 $end
$var wire 4 M out_buf [3:0] $end
$var wire 4 N in [3:0] $end
$var wire 1 : enabled_buf $end
$upscope $end
$scope module U12 $end
$var wire 1 - clk $end
$var wire 4 O in_acumulador [3:0] $end
$var wire 1 . reset $end
$var wire 1 < enabled_Acumulador $end
$var reg 4 P out_Acumulador [3:0] $end
$upscope $end
$scope module U13 $end
$var wire 4 Q in [3:0] $end
$var wire 4 R out_buf [3:0] $end
$var wire 1 9 enabled_buf $end
$upscope $end
$scope module U2 $end
$var wire 12 S address_ROM [11:0] $end
$var wire 8 T data_ROM [7:0] $end
$upscope $end
$scope module U3 $end
$var wire 1 - clk $end
$var wire 8 U in_fetch [7:0] $end
$var wire 1 . reset $end
$var wire 1 5 enabled_fetch $end
$var reg 8 V out_fetch [7:0] $end
$upscope $end
$scope module U4 $end
$var wire 1 - clk $end
$var wire 1 . reset $end
$var wire 1 = enabled_flags $end
$var wire 1 2 Ze $end
$var wire 1 B C $end
$var reg 1 ) C_1 $end
$var reg 1 " Z_1 $end
$upscope $end
$scope module U5 $end
$var wire 1 - clk $end
$var wire 1 . reset $end
$var reg 1 5 out_ph $end
$upscope $end
$scope module U6 $end
$var wire 1 ) C $end
$var wire 1 " Ze $end
$var wire 4 W instr [3:0] $end
$var wire 1 5 phase $end
$var wire 12 X out [11:0] $end
$var reg 7 Y Din [6:0] $end
$var reg 3 Z S [2:0] $end
$var reg 1 A csRAM $end
$var reg 1 @ incPC $end
$var reg 1 > loadA $end
$var reg 1 = loadFlags $end
$var reg 1 < loadOut $end
$var reg 1 ; loadPC $end
$var reg 1 : oeALU $end
$var reg 1 9 oeIN $end
$var reg 1 8 oeOprnd $end
$var reg 1 3 weRAM $end
$upscope $end
$scope module U7 $end
$var wire 12 [ address_RAM [11:0] $end
$var wire 1 A csRAM $end
$var wire 4 \ data_RAM [3:0] $end
$var wire 1 3 weRAM $end
$var reg 4 ] out_data [3:0] $end
$upscope $end
$scope module U8 $end
$var wire 1 8 enabled_buf $end
$var wire 4 ^ in [3:0] $end
$var wire 4 _ out_buf [3:0] $end
$upscope $end
$scope module U9 $end
$var wire 4 ` A [3:0] $end
$var wire 4 a B [3:0] $end
$var wire 3 b S [2:0] $end
$var wire 1 2 Z_alu $end
$var wire 4 c Y [3:0] $end
$var wire 1 B C_alu $end
$var reg 5 d P [4:0] $end
$upscope $end
$upscope $end
$upscope $end
$enddefinitions $end
#0
$dumpvars
bx d
bx c
bx b
bx a
bx `
bx _
bx ^
bx ]
bx \
bx [
bx Z
bx Y
bx X
bx W
bx V
bx U
bx T
bx S
bx R
bx Q
bx P
bx O
bx N
bx M
bx L
bx K
bx J
bx I
bx H
bx G
bx F
bx E
bx D
bx C
xB
xA
x@
bx ?
x>
x=
x<
x;
x:
x9
x8
bx 7
bx 6
x5
bx 4
x3
x2
bx 1
bx 0
r0 /
0.
1-
bx ,
bx +
bx *
x)
bx (
bx '
bx &
bx %
x$
bx #
x"
bx !
$end
#1
b0 !
b0 0
b0 M
b0 O
b0 R
b0 \
b0 _
b0 a
0B
b0 C
b0 K
b0 N
b0 c
12
b1000 X
b0 d
b0 F
b0 Z
b0 b
0<
08
09
1:
03
0A
0=
0>
0;
1@
b0 Y
b0 &
b0 7
b0 ^
b0 '
b0 ?
b0 W
b0 (
b0 G
b0 P
b0 +
b0 E
b0 L
b0 `
0$
05
0"
0)
b0 V
b1001001 [
b1001001 H
b1001001 *
b1001001 D
b1001001 #
b1001001 4
b1001001 T
b1001001 U
b0 %
b0 6
b0 I
b0 J
b0 S
1.
#2
b110 ,
b110 1
b110 Q
0.
#5
0-
#10
b1001 C
b1001 K
b1001 N
b1001 c
02
b1001 d
b1001 !
b1001 0
b1001 M
b1001 O
b1001 R
b1001 \
b1001 _
b1001 a
b11010000010 X
b10 F
b10 Z
b10 b
18
0:
1=
1>
0@
b1001 &
b1001 7
b1001 ^
b100 '
b100 ?
b100 W
b100001 Y
b100101010000 [
b100101010000 H
b100101010000 *
b100101010000 D
b1010000 #
b1010000 4
b1010000 T
b1010000 U
b1 %
b1 6
b1 I
b1 J
b1 S
b1001001 V
1$
15
1-
#15
0-
#20
b1000 X
b1001 !
b1001 0
b1001 M
b1001 O
b1001 R
b1001 \
b1001 _
b1001 a
r70 /
b0 F
b0 Z
b0 b
08
1:
0=
0>
1@
b101000 Y
b1010000 [
b1010000 H
b1010000 *
b1010000 D
b0 &
b0 7
b0 ^
b101 '
b101 ?
b101 W
b1001 +
b1001 E
b1001 L
b1001 `
0$
05
b1010000 V
1-
#25
0-
#30
b110 C
b110 K
b110 N
b110 c
b110 d
b110 !
b110 0
b110 M
b110 O
b110 R
b110 \
b110 _
b110 a
b11010000100 X
b10 F
b10 Z
b10 b
19
0:
1=
1>
0@
b101001 Y
b11010000 [
b11010000 H
b11010000 *
b11010000 D
b11010000 #
b11010000 4
b11010000 T
b11010000 U
b10 %
b10 6
b10 I
b10 J
b10 S
1$
15
1-
#35
0-
#40
b1000 X
r103 /
b0 F
b0 Z
b0 b
09
1:
0=
0>
1@
b1101000 Y
b1101 '
b1101 ?
b1101 W
b110 +
b110 E
b110 L
b110 `
0$
05
b11010000 V
1-
#45
0-
#50
b1001 X
1<
0@
b1101001 Y
b10101001 [
b10101001 H
b10101001 *
b10101001 D
b10101001 #
b10101001 4
b10101001 T
b10101001 U
b11 %
b11 6
b11 I
b11 J
b11 S
1$
15
1-
#55
0-
#60
b1000 X
r136 /
0<
1@
b1010000 Y
b100110101001 [
b100110101001 H
b100110101001 *
b100110101001 D
b1001 &
b1001 7
b1001 ^
b1010 '
b1010 ?
b1010 W
b110 (
b110 G
b110 P
0$
05
b10101001 V
1-
#65
0-
#70
b1111 C
b1111 K
b1111 N
b1111 c
b1111 d
b1001 !
b1001 0
b1001 M
b1001 O
b1001 R
b1001 \
b1001 _
b1001 a
b11011000010 X
b11 F
b11 Z
b11 b
18
0:
1=
1>
0@
b1010001 Y
b100110100001 [
b100110100001 H
b100110100001 *
b100110100001 D
b10100001 #
b10100001 4
b10100001 T
b10100001 U
b100 %
b100 6
b100 I
b100 J
b100 S
1$
15
1-
#75
0-
