Laboratorio #3/02_Tabla_SOP/tabla02SOP.v
module tablas2();

//SOP de la tabla 2

//Declaracion de variables

reg A, B, C;
wire s1, s2, s3, out;

// compuertas y conexiones
and U1(s1, ~A,~B, C);
and U2(s2, A, B, ~C);
and U3(s3, A, B, C);

or U6(out, s1,s2,s3);

//inicio de la simulacion
initial begin

  A = 0; B = 0; C = 0;

  $display("A  B  C  | Y");
  $display("---------|--");
  $monitor("%b  %b  %b  | %b", A, B, C, out);

  #1 C = 1;
  #1 B = 1; C = 0;
  #1 B = 1; C = 1;
  #1 A = 1; B = 0; C = 0;
  #1 A = 1; B = 0; C = 1;
  #1 A = 1; B = 1; C = 0;
  #1 A = 1; B = 1; C = 1;
  #1 $finish;
  end

  initial begin
    $dumpfile("tabla02SOP_tb.vcd");
    $dumpvars(0, tablas2);
    end

endmodule

Laboratorio 3/02_Tabla_SOP/tabla02SOP_tb.vcd
$date
	Sat Aug 01 01:15:56 2020
$end
$version
	Icarus Verilog
$end
$timescale
	1s
$end
$scope module tablas2 $end
$var wire 1 ! out $end
$var wire 1 " s1 $end
$var wire 1 # s2 $end
$var wire 1 $ s3 $end
$var reg 1 % A $end
$var reg 1 & B $end
$var reg 1 ' C $end
$upscope $end
$enddefinitions $end
#0
$dumpvars
0'
0&
0%
0$
0#
0"
0!
$end
#1
1!
1"
1'
#2
0!
0"
0'
1&
#3
1'
#4
0'
0&
1%
#5
1'
#6
1!
1#
0'
1&
#7
0#
1$
1'
