Laboratorio #3/01_Tabla_POS/tabla01POS.v
module tablas1();

//POS de la tabla 1

//Declaracion de variables

reg A, B, C;
wire s1, s2, s3, out;

or U1(s1, A,B, ~C);
or U2(s2, A, ~B, ~C);
or U3(s3, ~A, ~B, C);
and U4(out, s1,s2,s3);

initial begin
  A = 0; B = 0; C = 0;

  $display("A  B  C  | Y");
  $display("---------|--");
  $monitor("%b  %b  %b  | %b", A, B, C, out);

  #1 C = 1;
  #1 B = 1; C = 0;
  #1 B = 1; C = 1;
  #1 A = 1; B = 0; C = 0;
  #1 A = 1; B = 0; C = 1;
  #1 A = 1; B = 1; C = 0;
  #1 A = 1; B = 1; C = 1;
  #1 $finish;
  end

  initial begin
  $dumpfile("tabla01POS_tb.vcd");
  $dumpvars(0, tablas1);
  end


endmodule

Laboratorio 3/01_Tabla_POS/tabla01POS_tb.vcd
$date
	Sat Aug 01 01:11:53 2020
$end
$version
	Icarus Verilog
$end
$timescale
	1s
$end
$scope module tablas1 $end
$var wire 1 ! out $end
$var wire 1 " s1 $end
$var wire 1 # s2 $end
$var wire 1 $ s3 $end
$var reg 1 % A $end
$var reg 1 & B $end
$var reg 1 ' C $end
$upscope $end
$enddefinitions $end
#0
$dumpvars
0'
0&
0%
1$
1#
1"
1!
$end
#1
0!
0"
1'
#2
1!
1"
0'
1&
#3
0!
0#
1'
#4
1!
1#
0'
0&
1%
#5
1'
#6
0!
0$
0'
1&
#7
1!
1$
1'
