Laboratorio #8/Lab #8 contador/contador12.v

// Laboratorio #8 -- contador de 12 bits
// Entrada = clock de se;al del reloj
// salida = 12 bits del contador

module counter12(input clk, output [11:0]data  );

wire clk;

reg [11:0]data = 0;  //salida de los 12 bits

    always @ (posedge clk) begin    // cuenta en cada flanco de reloj
  
    data <= data + 1;

    end

endmodule //counter12

Laboratorio #8/Lab #8 contador/contador12_tb.v
// Testbench del contador
`define simulation

module testbench ();

reg clk = 0;              // registro de la senal del reloj
wire [11:0]data;          // Datos de salida
reg [11:0] ver_cont = 1; // Un registro para verificar si el contador cuenta correctamente

// Iniciar el contador
counter12 U1(.clk(clk),.data(data));

always #1 clk = ~clk;   // Se genera la senal de reloj

always @ (posedge clk ) begin
    if (ver_cont != data)
    $display(" LOAD = %d - LEIDO: %d", ver_cont, data);

    ver_cont <= ver_cont + 1;   //verificar si el contador cumple con los valoresm
end

initial begin
  // Mostrar los resultados en los diagramas de timng
  $dumpfile("contador12_tb.vcd");
  $dumpvars(0, testbench);

  // Se comprueba el Reset
  # 0.5 if (data != 0)
          $display("ERROR! Contador NO está a 0!");  //se muestra el error si el reset no esta en cero
        else
          $display("Contador inicializado. OK."); //  si esta en cero, se empieza el contador

  # 250 $display("FIN de la simulacion");   // cuando el contador llegue a 200 para la simulacion
  # 251 $finish;  // en 201 se termina la simulacion
end

// Se termina en 251 par que no sea tan larga la simulacion y se muestren todos los datos en los diagramas
// pero si llega  alos  11 bits de conteo

endmodule //testbench

Laboratorio #8/Lab #8 contador/contador12_tb.vcd
$date
	Sat Oct 24 23:21:10 2020
$end
$version
	Icarus Verilog
$end
$timescale
	1s
$end
$scope module testbench $end
$var wire 12 ! data [11:0] $end
$var reg 1 " clk $end
$var reg 12 # ver_cont [11:0] $end
$scope module U1 $end
$var wire 1 " clk $end
$var reg 12 $ data [11:0] $end
$upscope $end
$upscope $end
$enddefinitions $end
#0
$dumpvars
b0 $
b1 #
0"
b0 !
$end
#1
b1 !
b1 $
b10 #
1"
#2
0"
#3
b11 #
b10 !
b10 $
1"
#4
0"
#5
b11 !
b11 $
b100 #
1"
#6
0"
#7
b101 #
b100 !
b100 $
1"
#8
0"
#9
b101 !
b101 $
b110 #
1"
#10
0"
#11
b111 #
b110 !
b110 $
1"
#12
0"
#13
b111 !
b111 $
b1000 #
1"
#14
0"
#15
b1001 #
b1000 !
b1000 $
1"
#16
0"
#17
b1001 !
b1001 $
b1010 #
1"
#18
0"
#19
b1011 #
b1010 !
b1010 $
1"
#20
0"
#21
b1011 !
b1011 $
b1100 #
1"
#22
0"
#23
b1101 #
b1100 !
b1100 $
1"
#24
0"
#25
b1101 !
b1101 $
b1110 #
1"
#26
0"
#27
b1111 #
b1110 !
b1110 $
1"
#28
0"
#29
b1111 !
b1111 $
b10000 #
1"
#30
0"
#31
b10001 #
b10000 !
b10000 $
1"
#32
0"
#33
b10001 !
b10001 $
b10010 #
1"
#34
0"
#35
b10011 #
b10010 !
b10010 $
1"
#36
0"
#37
b10011 !
b10011 $
b10100 #
1"
#38
0"
#39
b10101 #
b10100 !
b10100 $
1"
#40
0"
#41
b10101 !
b10101 $
b10110 #
1"
#42
0"
#43
b10111 #
b10110 !
b10110 $
1"
#44
0"
#45
b10111 !
b10111 $
b11000 #
1"
#46
0"
#47
b11001 #
b11000 !
b11000 $
1"
#48
0"
#49
b11001 !
b11001 $
b11010 #
1"
#50
0"
#51
b11011 #
b11010 !
b11010 $
1"
#52
0"
#53
b11011 !
b11011 $
b11100 #
1"
#54
0"
#55
b11101 #
b11100 !
b11100 $
1"
#56
0"
#57
b11101 !
b11101 $
b11110 #
1"
#58
0"
#59
b11111 #
b11110 !
b11110 $
1"
#60
0"
#61
b11111 !
b11111 $
b100000 #
1"
#62
0"
#63
b100001 #
b100000 !
b100000 $
1"
#64
0"
#65
b100001 !
b100001 $
b100010 #
1"
#66
0"
#67
b100011 #
b100010 !
b100010 $
1"
#68
0"
#69
b100011 !
b100011 $
b100100 #
1"
#70
0"
#71
b100101 #
b100100 !
b100100 $
1"
#72
0"
#73
b100101 !
b100101 $
b100110 #
1"
#74
0"
#75
b100111 #
b100110 !
b100110 $
1"
#76
0"
#77
b100111 !
b100111 $
b101000 #
1"
#78
0"
#79
b101001 #
b101000 !
b101000 $
1"
#80
0"
#81
b101001 !
b101001 $
b101010 #
1"
#82
0"
#83
b101011 #
b101010 !
b101010 $
1"
#84
0"
#85
b101011 !
b101011 $
b101100 #
1"
#86
0"
#87
b101101 #
b101100 !
b101100 $
1"
#88
0"
#89
b101101 !
b101101 $
b101110 #
1"
#90
0"
#91
b101111 #
b101110 !
b101110 $
1"
#92
0"
#93
b101111 !
b101111 $
b110000 #
1"
#94
0"
#95
b110001 #
b110000 !
b110000 $
1"
#96
0"
#97
b110001 !
b110001 $
b110010 #
1"
#98
0"
#99
b110011 #
b110010 !
b110010 $
1"
#100
0"
#101
b110011 !
b110011 $
b110100 #
1"
#102
0"
#103
b110101 #
b110100 !
b110100 $
1"
#104
0"
#105
b110101 !
b110101 $
b110110 #
1"
#106
0"
#107
b110111 #
b110110 !
b110110 $
1"
#108
0"
#109
b110111 !
b110111 $
b111000 #
1"
#110
0"
#111
b111001 #
b111000 !
b111000 $
1"
#112
0"
#113
b111001 !
b111001 $
b111010 #
1"
#114
0"
#115
b111011 #
b111010 !
b111010 $
1"
#116
0"
#117
b111011 !
b111011 $
b111100 #
1"
#118
0"
#119
b111101 #
b111100 !
b111100 $
1"
#120
0"
#121
b111101 !
b111101 $
b111110 #
1"
#122
0"
#123
b111111 #
b111110 !
b111110 $
1"
#124
0"
#125
b111111 !
b111111 $
b1000000 #
1"
#126
0"
#127
b1000001 #
b1000000 !
b1000000 $
1"
#128
0"
#129
b1000001 !
b1000001 $
b1000010 #
1"
#130
0"
#131
b1000011 #
b1000010 !
b1000010 $
1"
#132
0"
#133
b1000011 !
b1000011 $
b1000100 #
1"
#134
0"
#135
b1000101 #
b1000100 !
b1000100 $
1"
#136
0"
#137
b1000101 !
b1000101 $
b1000110 #
1"
#138
0"
#139
b1000111 #
b1000110 !
b1000110 $
1"
#140
0"
#141
b1000111 !
b1000111 $
b1001000 #
1"
#142
0"
#143
b1001001 #
b1001000 !
b1001000 $
1"
#144
0"
#145
b1001001 !
b1001001 $
b1001010 #
1"
#146
0"
#147
b1001011 #
b1001010 !
b1001010 $
1"
#148
0"
#149
b1001011 !
b1001011 $
b1001100 #
1"
#150
0"
#151
b1001101 #
b1001100 !
b1001100 $
1"
#152
0"
#153
b1001101 !
b1001101 $
b1001110 #
1"
#154
0"
#155
b1001111 #
b1001110 !
b1001110 $
1"
#156
0"
#157
b1001111 !
b1001111 $
b1010000 #
1"
#158
0"
#159
b1010001 #
b1010000 !
b1010000 $
1"
#160
0"
#161
b1010001 !
b1010001 $
b1010010 #
1"
#162
0"
#163
b1010011 #
b1010010 !
b1010010 $
1"
#164
0"
#165
b1010011 !
b1010011 $
b1010100 #
1"
#166
0"
#167
b1010101 #
b1010100 !
b1010100 $
1"
#168
0"
#169
b1010101 !
b1010101 $
b1010110 #
1"
#170
0"
#171
b1010111 #
b1010110 !
b1010110 $
1"
#172
0"
#173
b1010111 !
b1010111 $
b1011000 #
1"
#174
0"
#175
b1011001 #
b1011000 !
b1011000 $
1"
#176
0"
#177
b1011001 !
b1011001 $
b1011010 #
1"
#178
0"
#179
b1011011 #
b1011010 !
b1011010 $
1"
#180
0"
#181
b1011011 !
b1011011 $
b1011100 #
1"
#182
0"
#183
b1011101 #
b1011100 !
b1011100 $
1"
#184
0"
#185
b1011101 !
b1011101 $
b1011110 #
1"
#186
0"
#187
b1011111 #
b1011110 !
b1011110 $
1"
#188
0"
#189
b1011111 !
b1011111 $
b1100000 #
1"
#190
0"
#191
b1100001 #
b1100000 !
b1100000 $
1"
#192
0"
#193
b1100001 !
b1100001 $
b1100010 #
1"
#194
0"
#195
b1100011 #
b1100010 !
b1100010 $
1"
#196
0"
#197
b1100011 !
b1100011 $
b1100100 #
1"
#198
0"
#199
b1100101 #
b1100100 !
b1100100 $
1"
#200
0"
#201
b1100101 !
b1100101 $
b1100110 #
1"
#202
0"
#203
b1100111 #
b1100110 !
b1100110 $
1"
#204
0"
#205
b1100111 !
b1100111 $
b1101000 #
1"
#206
0"
#207
b1101001 #
b1101000 !
b1101000 $
1"
#208
0"
#209
b1101001 !
b1101001 $
b1101010 #
1"
#210
0"
#211
b1101011 #
b1101010 !
b1101010 $
1"
#212
0"
#213
b1101011 !
b1101011 $
b1101100 #
1"
#214
0"
#215
b1101101 #
b1101100 !
b1101100 $
1"
#216
0"
#217
b1101101 !
b1101101 $
b1101110 #
1"
#218
0"
#219
b1101111 #
b1101110 !
b1101110 $
1"
#220
0"
#221
b1101111 !
b1101111 $
b1110000 #
1"
#222
0"
#223
b1110001 #
b1110000 !
b1110000 $
1"
#224
0"
#225
b1110001 !
b1110001 $
b1110010 #
1"
#226
0"
#227
b1110011 #
b1110010 !
b1110010 $
1"
#228
0"
#229
b1110011 !
b1110011 $
b1110100 #
1"
#230
0"
#231
b1110101 #
b1110100 !
b1110100 $
1"
#232
0"
#233
b1110101 !
b1110101 $
b1110110 #
1"
#234
0"
#235
b1110111 #
b1110110 !
b1110110 $
1"
#236
0"
#237
b1110111 !
b1110111 $
b1111000 #
1"
#238
0"
#239
b1111001 #
b1111000 !
b1111000 $
1"
#240
0"
#241
b1111001 !
b1111001 $
b1111010 #
1"
#242
0"
#243
b1111011 #
b1111010 !
b1111010 $
1"
#244
0"
#245
b1111011 !
b1111011 $
b1111100 #
1"
#246
0"
#247
b1111101 #
b1111100 !
b1111100 $
1"
#248
0"
#249
b1111101 !
b1111101 $
b1111110 #
1"
#250
0"
#251
b1111111 #
b1111110 !
b1111110 $
1"
#252
0"
#253
b1111111 !
b1111111 $
b10000000 #
1"
#254
0"
#255
b10000001 #
b10000000 !
b10000000 $
1"
#256
0"
#257
b10000001 !
b10000001 $
b10000010 #
1"
#258
0"
#259
b10000011 #
b10000010 !
b10000010 $
1"
#260
0"
#261
b10000011 !
b10000011 $
b10000100 #
1"
#262
0"
#263
b10000101 #
b10000100 !
b10000100 $
1"
#264
0"
#265
b10000101 !
b10000101 $
b10000110 #
1"
#266
0"
#267
b10000111 #
b10000110 !
b10000110 $
1"
#268
0"
#269
b10000111 !
b10000111 $
b10001000 #
1"
#270
0"
#271
b10001001 #
b10001000 !
b10001000 $
1"
#272
0"
#273
b10001001 !
b10001001 $
b10001010 #
1"
#274
0"
#275
b10001011 #
b10001010 !
b10001010 $
1"
#276
0"
#277
b10001011 !
b10001011 $
b10001100 #
1"
#278
0"
#279
b10001101 #
b10001100 !
b10001100 $
1"
#280
0"
#281
b10001101 !
b10001101 $
b10001110 #
1"
#282
0"
#283
b10001111 #
b10001110 !
b10001110 $
1"
#284
0"
#285
b10001111 !
b10001111 $
b10010000 #
1"
#286
0"
#287
b10010001 #
b10010000 !
b10010000 $
1"
#288
0"
#289
b10010001 !
b10010001 $
b10010010 #
1"
#290
0"
#291
b10010011 #
b10010010 !
b10010010 $
1"
#292
0"
#293
b10010011 !
b10010011 $
b10010100 #
1"
#294
0"
#295
b10010101 #
b10010100 !
b10010100 $
1"
#296
0"
#297
b10010101 !
b10010101 $
b10010110 #
1"
#298
0"
#299
b10010111 #
b10010110 !
b10010110 $
1"
#300
0"
#301
b10010111 !
b10010111 $
b10011000 #
1"
#302
0"
#303
b10011001 #
b10011000 !
b10011000 $
1"
#304
0"
#305
b10011001 !
b10011001 $
b10011010 #
1"
#306
0"
#307
b10011011 #
b10011010 !
b10011010 $
1"
#308
0"
#309
b10011011 !
b10011011 $
b10011100 #
1"
#310
0"
#311
b10011101 #
b10011100 !
b10011100 $
1"
#312
0"
#313
b10011101 !
b10011101 $
b10011110 #
1"
#314
0"
#315
b10011111 #
b10011110 !
b10011110 $
1"
#316
0"
#317
b10011111 !
b10011111 $
b10100000 #
1"
#318
0"
#319
b10100001 #
b10100000 !
b10100000 $
1"
#320
0"
#321
b10100001 !
b10100001 $
b10100010 #
1"
#322
0"
#323
b10100011 #
b10100010 !
b10100010 $
1"
#324
0"
#325
b10100011 !
b10100011 $
b10100100 #
1"
#326
0"
#327
b10100101 #
b10100100 !
b10100100 $
1"
#328
0"
#329
b10100101 !
b10100101 $
b10100110 #
1"
#330
0"
#331
b10100111 #
b10100110 !
b10100110 $
1"
#332
0"
#333
b10100111 !
b10100111 $
b10101000 #
1"
#334
0"
#335
b10101001 #
b10101000 !
b10101000 $
1"
#336
0"
#337
b10101001 !
b10101001 $
b10101010 #
1"
#338
0"
#339
b10101011 #
b10101010 !
b10101010 $
1"
#340
0"
#341
b10101011 !
b10101011 $
b10101100 #
1"
#342
0"
#343
b10101101 #
b10101100 !
b10101100 $
1"
#344
0"
#345
b10101101 !
b10101101 $
b10101110 #
1"
#346
0"
#347
b10101111 #
b10101110 !
b10101110 $
1"
#348
0"
#349
b10101111 !
b10101111 $
b10110000 #
1"
#350
0"
#351
b10110001 #
b10110000 !
b10110000 $
1"
#352
0"
#353
b10110001 !
b10110001 $
b10110010 #
1"
#354
0"
#355
b10110011 #
b10110010 !
b10110010 $
1"
#356
0"
#357
b10110011 !
b10110011 $
b10110100 #
1"
#358
0"
#359
b10110101 #
b10110100 !
b10110100 $
1"
#360
0"
#361
b10110101 !
b10110101 $
b10110110 #
1"
#362
0"
#363
b10110111 #
b10110110 !
b10110110 $
1"
#364
0"
#365
b10110111 !
b10110111 $
b10111000 #
1"
#366
0"
#367
b10111001 #
b10111000 !
b10111000 $
1"
#368
0"
#369
b10111001 !
b10111001 $
b10111010 #
1"
#370
0"
#371
b10111011 #
b10111010 !
b10111010 $
1"
#372
0"
#373
b10111011 !
b10111011 $
b10111100 #
1"
#374
0"
#375
b10111101 #
b10111100 !
b10111100 $
1"
#376
0"
#377
b10111101 !
b10111101 $
b10111110 #
1"
#378
0"
#379
b10111111 #
b10111110 !
b10111110 $
1"
#380
0"
#381
b10111111 !
b10111111 $
b11000000 #
1"
#382
0"
#383
b11000001 #
b11000000 !
b11000000 $
1"
#384
0"
#385
b11000001 !
b11000001 $
b11000010 #
1"
#386
0"
#387
b11000011 #
b11000010 !
b11000010 $
1"
#388
0"
#389
b11000011 !
b11000011 $
b11000100 #
1"
#390
0"
#391
b11000101 #
b11000100 !
b11000100 $
1"
#392
0"
#393
b11000101 !
b11000101 $
b11000110 #
1"
#394
0"
#395
b11000111 #
b11000110 !
b11000110 $
1"
#396
0"
#397
b11000111 !
b11000111 $
b11001000 #
1"
#398
0"
#399
b11001001 #
b11001000 !
b11001000 $
1"
#400
0"
#401
b11001001 !
b11001001 $
b11001010 #
1"
#402
0"
#403
b11001011 #
b11001010 !
b11001010 $
1"
#404
0"
#405
b11001011 !
b11001011 $
b11001100 #
1"
#406
0"
#407
b11001101 #
b11001100 !
b11001100 $
1"
#408
0"
#409
b11001101 !
b11001101 $
b11001110 #
1"
#410
0"
#411
b11001111 #
b11001110 !
b11001110 $
1"
#412
0"
#413
b11001111 !
b11001111 $
b11010000 #
1"
#414
0"
#415
b11010001 #
b11010000 !
b11010000 $
1"
#416
0"
#417
b11010001 !
b11010001 $
b11010010 #
1"
#418
0"
#419
b11010011 #
b11010010 !
b11010010 $
1"
#420
0"
#421
b11010011 !
b11010011 $
b11010100 #
1"
#422
0"
#423
b11010101 #
b11010100 !
b11010100 $
1"
#424
0"
#425
b11010101 !
b11010101 $
b11010110 #
1"
#426
0"
#427
b11010111 #
b11010110 !
b11010110 $
1"
#428
0"
#429
b11010111 !
b11010111 $
b11011000 #
1"
#430
0"
#431
b11011001 #
b11011000 !
b11011000 $
1"
#432
0"
#433
b11011001 !
b11011001 $
b11011010 #
1"
#434
0"
#435
b11011011 #
b11011010 !
b11011010 $
1"
#436
0"
#437
b11011011 !
b11011011 $
b11011100 #
1"
#438
0"
#439
b11011101 #
b11011100 !
b11011100 $
1"
#440
0"
#441
b11011101 !
b11011101 $
b11011110 #
1"
#442
0"
#443
b11011111 #
b11011110 !
b11011110 $
1"
#444
0"
#445
b11011111 !
b11011111 $
b11100000 #
1"
#446
0"
#447
b11100001 #
b11100000 !
b11100000 $
1"
#448
0"
#449
b11100001 !
b11100001 $
b11100010 #
1"
#450
0"
#451
b11100011 #
b11100010 !
b11100010 $
1"
#452
0"
#453
b11100011 !
b11100011 $
b11100100 #
1"
#454
0"
#455
b11100101 #
b11100100 !
b11100100 $
1"
#456
0"
#457
b11100101 !
b11100101 $
b11100110 #
1"
#458
0"
#459
b11100111 #
b11100110 !
b11100110 $
1"
#460
0"
#461
b11100111 !
b11100111 $
b11101000 #
1"
#462
0"
#463
b11101001 #
b11101000 !
b11101000 $
1"
#464
0"
#465
b11101001 !
b11101001 $
b11101010 #
1"
#466
0"
#467
b11101011 #
b11101010 !
b11101010 $
1"
#468
0"
#469
b11101011 !
b11101011 $
b11101100 #
1"
#470
0"
#471
b11101101 #
b11101100 !
b11101100 $
1"
#472
0"
#473
b11101101 !
b11101101 $
b11101110 #
1"
#474
0"
#475
b11101111 #
b11101110 !
b11101110 $
1"
#476
0"
#477
b11101111 !
b11101111 $
b11110000 #
1"
#478
0"
#479
b11110001 #
b11110000 !
b11110000 $
1"
#480
0"
#481
b11110001 !
b11110001 $
b11110010 #
1"
#482
0"
#483
b11110011 #
b11110010 !
b11110010 $
1"
#484
0"
#485
b11110011 !
b11110011 $
b11110100 #
1"
#486
0"
#487
b11110101 #
b11110100 !
b11110100 $
1"
#488
0"
#489
b11110101 !
b11110101 $
b11110110 #
1"
#490
0"
#491
b11110111 #
b11110110 !
b11110110 $
1"
#492
0"
#493
b11110111 !
b11110111 $
b11111000 #
1"
#494
0"
#495
b11111001 #
b11111000 !
b11111000 $
1"
#496
0"
#497
b11111001 !
b11111001 $
b11111010 #
1"
#498
0"
#499
b11111011 #
b11111010 !
b11111010 $
1"
#500
0"
#501
b11111011 !
b11111011 $
b11111100 #
1"
