Laboratorio 3/04_Tabla_POS/tabla04P0S.v
module tablas4();

//POS de la tabla 4

//Declaracion de variables

reg A, B, C, D;
wire s1, s2, s3, s4, s5, s6, s7, s8, s9, out;

// compuertas y conexiones
or U1(s1, A, B, C, ~D);
or U2(s2, A, ~B, C, D);
or U3(s3, A, ~B, C, ~D);
or U4(s4, ~A, B, C, ~D);
or U5(s5, ~A, B, ~C, ~D);
or U6(s6, ~A, ~B, C, D);
or U7(s7, ~A, ~B, C, ~D);
or U8(s8, ~A, ~B, ~C, D);
or U9(s9, ~A, ~B, ~C, ~D);

and U10(out, s1,s2,s3,s4,s5,s6,s7,s8,s9);

//inicio de la simulacion
initial begin

  $display("A  B  C  D  |  Y");
  $display("------------|---");
  $monitor("%b  %b  %b  %b  |  %b", A, B, C, D, out);

  A = 0; B = 0; C = 0; D = 0;

  #1 D = 1;
  #1 C = 1; D = 0;
  #1 C = 1; D = 1;
  #1 B = 1; C = 0; D = 0;
  #1 B = 1; C = 0; D = 1;
  #1 B = 1; C = 1; D = 0;
  #1 B = 1; C = 1; D = 1;
  #1 A = 1; B = 0; C = 0; D = 0;
  #1 A = 1; B = 0; C = 0; D = 1;
  #1 A = 1; B = 0; C = 1; D = 0;
  #1 A = 1; B = 0; C = 1; D = 1;
  #1 A = 1; B = 1; C = 0; D = 0;
  #1 A = 1; B = 1; C = 0; D = 1;
  #1 A = 1; B = 1; C = 1; D = 0;
  #1 A = 1; B = 1; C = 1; D = 1;

  #1 $finish;
  end

  initial begin
  $dumpfile("tabla04POS_tb.vcd");
  $dumpvars(0, tablas4);
  end

endmodule

Laboratorio #3/04_Tabla_POS/tabla04POS_tb.vcd
$date
	Sat Aug 01 17:15:17 2020
$end
$version
	Icarus Verilog
$end
$timescale
	1s
$end
$scope module tablas4 $end
$var wire 1 ! out $end
$var wire 1 " s1 $end
$var wire 1 # s2 $end
$var wire 1 $ s3 $end
$var wire 1 % s4 $end
$var wire 1 & s5 $end
$var wire 1 ' s6 $end
$var wire 1 ( s7 $end
$var wire 1 ) s8 $end
$var wire 1 * s9 $end
$var reg 1 + A $end
$var reg 1 , B $end
$var reg 1 - C $end
$var reg 1 . D $end
$upscope $end
$enddefinitions $end
#0
$dumpvars
0.
0-
0,
0+
1*
1)
1(
1'
1&
1%
1$
1#
1"
1!
$end
#1
0!
0"
1.
#2
1!
1"
0.
1-
#3
1.
#4
0!
1$
0#
0.
0-
1,
#5
0!
0$
1#
1.
#6
1!
1$
0.
1-
#7
1.
#8
1!
1&
1%
0.
0-
0,
1+
#9
0!
0%
1.
#10
1!
1%
0.
1-
#11
0!
0&
1.
#12
1(
0'
1&
0.
0-
1,
#13
0!
0(
1'
1.
#14
0)
1(
0.
1-
#15
0!
0*
1)
1.
